MANIFEST.in
README.rst
isosolve.py
licence_en.txt
setup.py
version.txt
./isosolve.py
./version.txt
./doc/IsoSolve.pdf
./example/ALA_mapping.html
./example/ALA_mapping.md
./example/ALA_mapping.tsv
./example/ALA_mapping_inchi_cumo.tsv
./example/ALA_mapping_inchi_emu.tsv
./example/ALA_mapping_inchi_iso.tsv
./example/ALA_mapping_inchi_mcomb.tsv
./example/ALA_measurements.tsv
doc/IsoSolve.pdf
doc/html/.buildinfo
doc/html/genindex.html
doc/html/index.html
doc/html/isosolve.html
doc/html/manual.html
doc/html/modules.html
doc/html/notebook.html
doc/html/objects.inv
doc/html/py-modindex.html
doc/html/search.html
doc/html/searchindex.js
doc/html/_sources/index.rst.txt
doc/html/_sources/isosolve.rst.txt
doc/html/_sources/manual.rst.txt
doc/html/_sources/modules.rst.txt
doc/html/_static/ajax-loader.gif
doc/html/_static/basic.css
doc/html/_static/classic.css
doc/html/_static/comment-bright.png
doc/html/_static/comment-close.png
doc/html/_static/comment.png
doc/html/_static/default.css
doc/html/_static/doctools.js
doc/html/_static/documentation_options.js
doc/html/_static/down-pressed.png
doc/html/_static/down.png
doc/html/_static/file.png
doc/html/_static/jquery-3.2.1.js
doc/html/_static/jquery.js
doc/html/_static/language_data.js
doc/html/_static/minus.png
doc/html/_static/plus.png
doc/html/_static/pygments.css
doc/html/_static/searchtools.js
doc/html/_static/sidebar.js
doc/html/_static/underscore-1.3.1.js
doc/html/_static/underscore.js
doc/html/_static/up-pressed.png
doc/html/_static/up.png
doc/html/_static/websupport.js
example/ALA_mapping.html
example/ALA_mapping.md
example/ALA_mapping.tsv
example/ALA_mapping_inchi_cumo.tsv
example/ALA_mapping_inchi_emu.tsv
example/ALA_mapping_inchi_iso.tsv
example/ALA_mapping_inchi_mcomb.tsv
example/ALA_measurements.tsv
isosolve.egg-info/PKG-INFO
isosolve.egg-info/SOURCES.txt
isosolve.egg-info/dependency_links.txt
isosolve.egg-info/entry_points.txt
isosolve.egg-info/requires.txt
isosolve.egg-info/top_level.txt