Metadata-Version: 1.2
Name: isosolve
Version: 1.0.1
Summary: integrative framework for measurements of isotope labeling
Home-page: https://github.com/sgsokol/isosolve
Author: Serguei Sokol
Author-email: sokol@insa-toulouse.fr
License: GNU General Public License v2 or later (GPLv2+)
Project-URL: Documentation, https://readthedocs.org/isosolve
Project-URL: Source, https://github.com/sgsokol/isosolve
Project-URL: Tracker, https://github.com/sgsokol/isosolve/issues
Keywords: isotope labeling,least squares,symbolic solution
Platform: UNKNOWN
Classifier: Environment :: Console
Classifier: Intended Audience :: End Users/Desktop
Classifier: License :: OSI Approved :: GNU General Public License v2 (GPLv2)
Classifier: Operating System :: OS Independent
Classifier: Programming Language :: Python :: 3 :: Only
Classifier: Topic :: Scientific/Engineering :: Bio-Informatics
